language_server_protocol-1.0.1.data/scripts/lspsnitch
lsp/__init__.py
lsp/__main__.py
lsp/client.py
lsp/protocol.py
lsp/py.typed
lsp/lsp/__init__.py
lsp/lsp/client.py
lsp/lsp/common.py
lsp/lsp/messages.py
lsp/lsp/server.py
language_server_protocol-1.0.1.dist-info/LICENSE
language_server_protocol-1.0.1.dist-info/METADATA
language_server_protocol-1.0.1.dist-info/WHEEL
language_server_protocol-1.0.1.dist-info/top_level.txt
language_server_protocol-1.0.1.dist-info/RECORD
