Metadata-Version: 2.1
Name: language-server-protocol
Version: 1.0.1
Author: Joel Christiansen
License: Apache License
Project-URL: Documentation, https://language-server-protocol.readthedocs.io/en/latest/index.html
Project-URL: github, https://github.com/Thirdegree/language-server-protocol
Project-URL: Pypi, https://pypi.org/project/language-server-protocol/
Keywords: language,server,protocol
Classifier: Programming Language :: Python :: 3.11
Classifier: Topic :: Software Development
Classifier: Topic :: Software Development :: Libraries
Requires-Python: >=3.11
License-File: LICENSE
Requires-Dist: ujson (~=5.7)
